GetSequenceIoApiClient/__init__.py
GetSequenceIoApiClient/client.py
getsequenceioapiclient-0.1.2.dist-info/licenses/LICENSE
getsequenceioapiclient-0.1.2.dist-info/METADATA
getsequenceioapiclient-0.1.2.dist-info/WHEEL
getsequenceioapiclient-0.1.2.dist-info/top_level.txt
getsequenceioapiclient-0.1.2.dist-info/RECORD
