Metadata-Version: 2.4
Name: GetSequenceIoApiClient
Version: 0.1.2
Summary: Async Python client for Sequence financial orchestration platform API.
Author-email: Dyllan Macias <DellanX@Live.com>
License: MIT License
Project-URL: Homepage, https://github.com/DellanX/GetSequenceIoApiClient
Project-URL: Source, https://github.com/DellanX/GetSequenceIoApiClient
Requires-Python: >=3.10
License-File: LICENSE
Requires-Dist: aiohttp>=3.8.0
Provides-Extra: test
Requires-Dist: pytest; extra == "test"
Requires-Dist: pytest-cov; extra == "test"
Requires-Dist: pytest-asyncio; extra == "test"
Dynamic: license-file
